python_marketing_research_functions/__init__.py
python_marketing_research_functions/chapter10.py
python_marketing_research_functions/chapter11.py
python_marketing_research_functions/chapter2.py
python_marketing_research_functions/chapter3.py
python_marketing_research_functions/chapter6.py
python_marketing_research_functions/chapter7.py
python_marketing_research_functions/chapter8.py
python_marketing_research_functions/chapter9.py
python_marketing_research-0.9.4.dist-info/LICENSE
python_marketing_research-0.9.4.dist-info/METADATA
python_marketing_research-0.9.4.dist-info/WHEEL
python_marketing_research-0.9.4.dist-info/top_level.txt
python_marketing_research-0.9.4.dist-info/RECORD
