Metadata-Version: 2.1
Name: python-marketing-research
Version: 0.9.4
Summary: A package for Python for Marketing Research and Analytis
Home-page: https://github.com/python-marketing-research/python-marketing-research-1ed
Author: Jason Schwarz
Author-email: python-marketing@gmail.com
License: UNKNOWN
Platform: UNKNOWN
Classifier: Programming Language :: Python :: 3
Classifier: License :: OSI Approved :: Apache Software License
Classifier: Operating System :: OS Independent
Requires-Python: >=3.6
